tap_slack/__init__.py
tap_slack/catalog.py
tap_slack/client.py
tap_slack/streams.py
tap_slack/transform.py
tap_slack/schemas/channel_members.json
tap_slack/schemas/channels.json
tap_slack/schemas/files.json
tap_slack/schemas/messages.json
tap_slack/schemas/remote_files.json
tap_slack/schemas/teams.json
tap_slack/schemas/threads.json
tap_slack/schemas/user_groups.json
tap_slack/schemas/users.json
tests/__init__.py
tests/test_schemas.py
pipelinewise_tap_slack-1.1.1.dist-info/LICENSE
pipelinewise_tap_slack-1.1.1.dist-info/METADATA
pipelinewise_tap_slack-1.1.1.dist-info/WHEEL
pipelinewise_tap_slack-1.1.1.dist-info/entry_points.txt
pipelinewise_tap_slack-1.1.1.dist-info/top_level.txt
pipelinewise_tap_slack-1.1.1.dist-info/RECORD
