Metadata-Version: 2.1
Name: pipelinewise-tap-slack
Version: 1.1.1
Summary: Singer.io tap for extracting data from the Slack Web API - PipelineWise compatible
Home-page: https://github.com/transferwise/pipelinewise-tap-slack
Author: Wise
Classifier: License :: OSI Approved :: GNU Affero General Public License v3
Classifier: Programming Language :: Python :: 3 :: Only
Requires-Python: >=3.6
License-File: LICENSE
Requires-Dist: pipelinewise-singer-python (==1.*)
Requires-Dist: slack-sdk (==3.20.0)
Provides-Extra: test
Requires-Dist: pylint (==2.8.*) ; extra == 'test'
Requires-Dist: pytest (==6.2.*) ; extra == 'test'
Requires-Dist: pytest-cov (==2.12.*) ; extra == 'test'
